jlibs/__init__.py
jlibs/aws/__init__.py
jlibs/aws/accounts.py
jlibs/aws/athena.py
jlibs/aws/ec2/__init__.py
jlibs/aws/ec2/ami.py
jlibs/aws/ec2/instance.py
jlibs/file/__init__.py
jlibs/file/cache.py
jlibs/file/csv.py
jlibs-0.1.0.dist-info/LICENSE
jlibs-0.1.0.dist-info/METADATA
jlibs-0.1.0.dist-info/WHEEL
jlibs-0.1.0.dist-info/top_level.txt
jlibs-0.1.0.dist-info/RECORD
