Metadata-Version: 2.1
Name: jlibs
Version: 0.1.0
Summary: A collection of functions that leverage Boto3
Home-page: https://john.mariquit.com/projects/jlibs/
Author: John Anthony Mariquit
Author-email: john@mariquit.com
License: MIT License
Classifier: Programming Language :: Python :: 3.10
Classifier: License :: OSI Approved :: MIT License
Classifier: Development Status :: 3 - Alpha
Classifier: Intended Audience :: Developers
Requires-Python: >=3.10
License-File: LICENSE
Requires-Dist: boto3 (>=1.26)
